k8s_collector/__init__.py
k8s_collector/collectors/__init__.py
k8s_collector/collectors/k8s_collector.py
k8s_collector/config/__init__.py
k8s_collector/config/collector_config.schema.json
k8s_collector/config/models/__init__.py
k8s_collector/config/models/base.py
k8s_collector/config/models/sinks/__init__.py
k8s_collector/config/models/sinks/models.py
k8s_collector/config/models/sinks/console/__init__.py
k8s_collector/config/models/sinks/console/models.py
k8s_collector/config/models/sinks/http/__init__.py
k8s_collector/config/models/sinks/http/models.py
k8s_collector/config/parsers/__init__.py
k8s_collector/config/parsers/collector_config_parser.py
k8s_collector/config/parsers/dict_collector_config_parser.py
k8s_collector/config/parsers/exceptions.py
k8s_collector/config/parsers/yaml_collector_config_parser.py
k8s_collector/config/parsers/sinks/__init__.py
k8s_collector/config/parsers/sinks/console_sink_config_parser.py
k8s_collector/config/parsers/sinks/http_sink_config_parser.py
k8s_collector/config/parsers/sinks/sink_config_parser.py
k8s_collector/config/parsers/sinks/factory/__init__.py
k8s_collector/config/parsers/sinks/factory/basic_sink_config_parser_factory.py
k8s_collector/config/parsers/sinks/factory/sink_config_parser_factory.py
k8s_collector/config/validators/__init__.py
k8s_collector/config/validators/collector_config_validator.py
k8s_collector/config/validators/json_schema_collector_config_validator.py
k8s_collector/filterers/__init__.py
k8s_collector/filterers/filterer.py
k8s_collector/filterers/jmespath_filterer.py
k8s_collector/handlers/__init__.py
k8s_collector/handlers/basic_event_handler.py
k8s_collector/handlers/event_handler.py
k8s_collector/listeners/__init__.py
k8s_collector/listeners/basic_resource_listener.py
k8s_collector/listeners/resource_listener.py
k8s_collector/listeners/threaded_multi_resource_listener.py
k8s_collector/processors/__init__.py
k8s_collector/processors/jmespath_processor.py
k8s_collector/processors/processor.py
k8s_collector-0.0.8.dist-info/LICENSE.txt
k8s_collector-0.0.8.dist-info/METADATA
k8s_collector-0.0.8.dist-info/WHEEL
k8s_collector-0.0.8.dist-info/top_level.txt
k8s_collector-0.0.8.dist-info/RECORD
