Metadata-Version: 2.1
Name: k8s-collector
Version: 0.0.8
Summary: collect k8s objects, parse them with jmespath and send them to sink
Author-email: "A. Random Developer" <author@example.com>
Maintainer-email: "A. Great Maintainer" <maintainer@example.com>
License: Apache License
Project-URL: Homepage, https://github.com/EmilK322/k8s-collector
Project-URL: Bug Reports, https://github.com/EmilK322/k8s-collector/issues
Project-URL: Funding, https://donate.pypi.org
Project-URL: Source, https://github.com/EmilK322/k8s-collector
Keywords: sample,setuptools,development
Classifier: Development Status :: 3 - Alpha
Classifier: Intended Audience :: Developers
Classifier: Topic :: Software Development :: Build Tools
Classifier: License :: OSI Approved :: Apache Software License
Classifier: Programming Language :: Python :: 3
Classifier: Programming Language :: Python :: 3.10
Classifier: Programming Language :: Python :: 3.11
Classifier: Programming Language :: Python :: 3 :: Only
Requires-Python: >=3.10
License-File: LICENSE.txt
Requires-Dist: kubernetes ==27.2.0
Requires-Dist: jmespath ==1.0.1
Requires-Dist: PyYAML ==6.0.1
Requires-Dist: jsonschema ==4.19.1
Provides-Extra: all
Requires-Dist: k8s-collector[sink-http] ; extra == 'all'
Provides-Extra: sink-http
Requires-Dist: httpx ==0.25.0 ; extra == 'sink-http'
